{"is_source_file": false, "format": "", "description": "", "external_files": [], "external_methods": [], "published": [], "classes": [], "methods": [], "calls": [], "search-terms": ["CSS", "variables", "theme", "App", "responsive", "dark mode"], "state": 2, "file_id": 7, "knowledge_revision": 19, "git_revision": "ce58d5b7b28376e03679aad15f0ed63cc2364e2e", "hash": "22f9e17cc1848b56dbb244518ac2707e", "format-version": 4, "code-base-name": "todo_frontend", "filename": "todo_frontend/src/App.css", "revision_history": [{"19": "ce58d5b7b28376e03679aad15f0ed63cc2364e2e"}]}